[{"_id":"5ae70919b5db3b313047ab78","e1":"奥德赛","rel":"书名","e2":"奥德赛"},{"_id":"5ae70919b5db3b313047ab79","e1":"奥迪公司","rel":"外文名称","e2":"奥迪"},{"_id":"5ae70919b5db3b313047ab7a","e1":"离骚","rel":"作者","e2":"屈原"},{"_id":"5ae70919b5db3b313047ab7b","e1":"COC","rel":"缩写","e2":"COC"},{"_id":"5ae70919b5db3b313047ab7c","e1":"宝马1系","rel":"品牌","e2":"宝马"},{"_id":"5ae70919b5db3b313047ab7d","e1":"福特汽车环保奖","rel":"举办单位","e2":"福特汽车公司"},{"_id":"5ae70919b5db3b313047ab7e","e1":"华晨汽车工程研究院","rel":"公司名称","e2":"华晨汽车工程研究院"},{"_id":"5ae70919b5db3b313047ab7f","e1":"柯达公司","rel":"公司名称","e2":"柯达公司"},{"_id":"5ae70919b5db3b313047ab80","e1":"奥迪Q5","rel":"品牌","e2":"奥迪"},{"_id":"5ae70919b5db3b313047ab81","e1":"保时捷","rel":"BaiduTAG","e2":"保时捷"},{"_id":"5ae70919b5db3b313047ab82","e1":"福特","rel":"公司口号","e2":"福特"},{"_id":"5ae70919b5db3b313047ab83","e1":"保时捷911","rel":"品牌","e2":"保时捷"},{"_id":"5ae70919b5db3b313047ab84","e1":"华晨宝马汽车有限公司","rel":"公司名称","e2":"华晨宝马汽车有限公司"},{"_id":"5ae70919b5db3b313047ab85","e1":"威廉·迈巴赫","rel":"外文名","e2":"WilhelmMaybach"},{"_id":"5ae70919b5db3b313047ab86","e1":"宝马M3","rel":"品牌","e2":"宝马M3"},{"_id":"5ae70919b5db3b313047ab87","e1":"星宇股份","rel":"中文简称","e2":"星宇股份"},{"_id":"5ae70919b5db3b313047ab88","e1":"日产","rel":"公司名称","e2":"日产汽车公司"},{"_id":"5ae70919b5db3b313047ab89","e1":"菲亚特","rel":"公司名称","e2":"菲亚特"},{"_id":"5ae70919b5db3b313047ab8a","e1":"MPV","rel":"简称","e2":"MPV"},{"_id":"5ae70919b5db3b313047ab8b","e1":"大众集团","rel":"公司名称","e2":"大众集团"},{"_id":"5ae70919b5db3b313047ab8c","e1":"斯巴鲁","rel":"公司名称","e2":"斯巴鲁"},{"_id":"5ae70919b5db3b313047ab8d","e1":"德尔福","rel":"公司名称","e2":"德尔福"},{"_id":"5ae70919b5db3b313047ab8e","e1":"第二汽车制造厂","rel":"也称","e2":"二汽"},{"_id":"5ae70919b5db3b313047ab8f","e1":"丰田汽车公司","rel":"公司名称","e2":"丰田汽车公司"},{"_id":"5ae70919b5db3b313047ab90","e1":"萨博9-3","rel":"品牌","e2":"萨博"},{"_id":"5ae70919b5db3b313047ab91","e1":"沃尔沃","rel":"总部地点","e2":"瑞典哥德堡"},{"_id":"5ae70919b5db3b313047ab92","e1":"东风汽车有限公司","rel":"公司名称","e2":"东风汽车有限公司"},{"_id":"5ae70919b5db3b313047ab93","e1":"东风雪铁龙","rel":"公司名称","e2":"东风雪铁龙"},{"_id":"5ae70919b5db3b313047ab94","e1":"奥迪Q7","rel":"品牌","e2":"奥迪"},{"_id":"5ae70919b5db3b313047ab95","e1":"东风本田汽车有限公司","rel":"公司名称","e2":"东风本田汽车有限公司"},{"_id":"5ae70919b5db3b313047ab96","e1":"雷克萨斯","rel":"主要车型","e2":"ES"},{"_id":"5ae70919b5db3b313047ab97","e1":"戴姆勒","rel":"公司名称","e2":"戴姆勒股份公司"},{"_id":"5ae70919b5db3b313047ab98","e1":"阿斯顿·马丁","rel":"公司名称","e2":"阿斯顿·马丁"},{"_id":"5ae70919b5db3b313047ab99","e1":"王的盛宴","rel":"制片人","e2":"陆川"},{"_id":"5ae70919b5db3b313047ab9a","e1":"北美","rel":"包含","e2":"美国"},{"_id":"5ae70919b5db3b313047ab9b","e1":"王的盛宴","rel":"导演","e2":"陆川"},{"_id":"5ae70919b5db3b313047ab9c","e1":"北汽集团","rel":"公司名称","e2":"北汽集团"},{"_id":"5ae70919b5db3b313047ab9d","e1":"福睿斯","rel":"品牌","e2":"福睿斯"},{"_id":"5ae70919b5db3b313047ab9e","e1":"雷克萨斯","rel":"主要车型","e2":"LS"},{"_id":"5ae70919b5db3b313047ab9f","e1":"乐视","rel":"创始人","e2":"贾跃亭"},{"_id":"5ae70919b5db3b313047aba0","e1":"广汽传祺","rel":"品牌","e2":"广汽传祺"},{"_id":"5ae70919b5db3b313047aba1","e1":"邵景峰","rel":"国籍","e2":"中国"},{"_id":"5ae70919b5db3b313047aba2","e1":"通用汽车公司","rel":"公司名称","e2":"通用汽车公司"},{"_id":"5ae70919b5db3b313047aba3","e1":"陈清泰","rel":"国籍","e2":"中国"},{"_id":"5ae70919b5db3b313047aba4","e1":"宝马Z4","rel":"品牌","e2":"宝马"},{"_id":"5ae70919b5db3b313047aba5","e1":"iPhone","rel":"外文名","e2":"iPhone"},{"_id":"5ae70919b5db3b313047aba6","e1":"宝马6系","rel":"品牌","e2":"宝马"},{"_id":"5ae70919b5db3b313047aba7","e1":"西雅特","rel":"公司名称","e2":"西雅特"},{"_id":"5ae70919b5db3b313047aba8","e1":"陈光祖","rel":"国籍","e2":"中国"},{"_id":"5ae70919b5db3b313047aba9","e1":"凯迪拉克","rel":"总部地点","e2":"美国"},{"_id":"5ae70919b5db3b313047abaa","e1":"雷克萨斯","rel":"主要市场","e2":"欧洲"},{"_id":"5ae70919b5db3b313047abab","e1":"宝马3系","rel":"品牌","e2":"宝马3系"},{"_id":"5ae70919b5db3b313047abac","e1":"法拉利","rel":"主要农产品","e2":"California"},{"_id":"5ae70919b5db3b313047abad","e1":"一汽轿车","rel":"公司名称","e2":"一汽轿车股份有限公司"},{"_id":"5ae70919b5db3b313047abae","e1":"阿特兹","rel":"品牌","e2":"阿特兹"},{"_id":"5ae70919b5db3b313047abaf","e1":"雷克萨斯LS","rel":"品牌","e2":"雷克萨斯"},{"_id":"5ae70919b5db3b313047abb0","e1":"雷克萨斯","rel":"主要车型","e2":"LX"},{"_id":"5ae70919b5db3b313047abb1","e1":"北京汽车","rel":"全称","e2":"北京汽车股份有限公司"},{"_id":"5ae70919b5db3b313047abb2","e1":"长安铃木","rel":"公司名称","e2":"长安铃木"},{"_id":"5ae70919b5db3b313047abb3","e1":"美国国家公路交通安全管理局","rel":"外文名","e2":"NHTSA"},{"_id":"5ae70919b5db3b313047abb4","e1":"大众集团","rel":"旗下品牌","e2":"斯柯达"},{"_id":"5ae70919b5db3b313047abb5","e1":"宝马7系","rel":"品牌","e2":"宝马"},{"_id":"5ae70919b5db3b313047abb6","e1":"索尼","rel":"公司名称","e2":"索尼"},{"_id":"5ae70919b5db3b313047abb7","e1":"蓝凌","rel":"公司名称","e2":"蓝凌"},{"_id":"5ae70919b5db3b313047abb8","e1":"奥迪Q2","rel":"所属公司","e2":"奥迪"},{"_id":"5ae70919b5db3b313047abb9","e1":"宝马5系","rel":"品牌","e2":"宝马5系"},{"_id":"5ae70919b5db3b313047abba","e1":"杨学良","rel":"国籍","e2":"中国"},{"_id":"5ae70919b5db3b313047abbb","e1":"澳大利亚","rel":"简称","e2":"澳洲"},{"_id":"5ae70919b5db3b313047abbc","e1":"长安铃木锋驭","rel":"品牌","e2":"长安铃木"},{"_id":"5ae70919b5db3b313047abbd","e1":"东风汽车公司","rel":"公司名称","e2":"东风汽车公司"},{"_id":"5ae70919b5db3b313047abbe","e1":"春运","rel":"中文称呼","e2":"春运"},{"_id":"5ae70919b5db3b313047abbf","e1":"中铁物流集团有限公司","rel":"外文名称","e2":"CRLG"},{"_id":"5ae70919b5db3b313047abc0","e1":"鲁冠球","rel":"主要公司","e2":"万向集团"},{"_id":"5ae70919b5db3b313047abc1","e1":"韩红爱心慈善基金会","rel":"知名人物","e2":"韩红"},{"_id":"5ae70919b5db3b313047abc2","e1":"苏联","rel":"国家领袖","e2":"勃列日涅夫"},{"_id":"5ae70919b5db3b313047abc3","e1":"福特福克斯","rel":"生产厂家","e2":"福特"},{"_id":"5ae70919b5db3b313047abc4","e1":"宝马X3","rel":"BaiduTAG","e2":"宝马"},{"_id":"5ae70919b5db3b313047abc5","e1":"上汽集团","rel":"公司简称","e2":"上汽集团"},{"_id":"5ae70919b5db3b313047abc6","e1":"李书福","rel":"国籍","e2":"中国"},{"_id":"5ae70919b5db3b313047abc7","e1":"索兰托","rel":"生产厂家","e2":"起亚"},{"_id":"5ae70919b5db3b313047abc8","e1":"华晨宝马","rel":"公司名称","e2":"华晨宝马汽车有限公司"},{"_id":"5ae70919b5db3b313047abc9","e1":"奥迪Q8","rel":"生产厂家","e2":"奥迪公司"},{"_id":"5ae70919b5db3b313047abca","e1":"诺基亚","rel":"公司名称","e2":"诺基亚"},{"_id":"5ae70919b5db3b313047abcb","e1":"奥迪A6L","rel":"品牌","e2":"奥迪"},{"_id":"5ae70919b5db3b313047abcc","e1":"福睿斯","rel":"生产厂家","e2":"长安福特"},{"_id":"5ae70919b5db3b313047abcd","e1":"凤凰","rel":"中文学名","e2":"凤凰"},{"_id":"5ae70919b5db3b313047abce","e1":"雷克萨斯LS","rel":"生产厂家","e2":"雷克萨斯"},{"_id":"5ae70919b5db3b313047abcf","e1":"雷克萨斯","rel":"主要市场","e2":"北美"},{"_id":"5ae70919b5db3b313047abd0","e1":"德黑兰","rel":"所属地区","e2":"伊朗"},{"_id":"5ae70919b5db3b313047abd1","e1":"欧洲","rel":"BaiduTAG","e2":"欧洲"},{"_id":"5ae70919b5db3b313047abd2","e1":"新浪","rel":"公司名称","e2":"新浪"},{"_id":"5ae70919b5db3b313047abd3","e1":"成都","rel":"别名","e2":"蓉城"},{"_id":"5ae70919b5db3b313047abd4","e1":"CCPC","rel":"简称","e2":"CCPC"},{"_id":"5ae70919b5db3b313047abd5","e1":"宝马X3","rel":"品牌","e2":"宝马"},{"_id":"5ae70919b5db3b313047abd6","e1":"湖北","rel":"省委书记","e2":"李鸿忠"},{"_id":"5ae70919b5db3b313047abd7","e1":"中国兵器装备集团公司","rel":"其他名称","e2":"中国南方工业集团公司"},{"_id":"5ae70919b5db3b313047abd8","e1":"戴姆勒集团","rel":"公司名称","e2":"戴姆勒集团"},{"_id":"5ae70919b5db3b313047abd9","e1":"福特","rel":"公司名称","e2":"福特汽车公司"},{"_id":"5ae70919b5db3b313047abda","e1":"法兰克福车展","rel":"展会名称","e2":"法兰克福车展"},{"_id":"5ae70919b5db3b313047abdb","e1":"沃尔沃S60","rel":"品牌","e2":"沃尔沃"},{"_id":"5ae70919b5db3b313047abdc","e1":"奔驰S级","rel":"竞争对手","e2":"宝马7系"},{"_id":"5ae70919b5db3b313047abdd","e1":"丁超","rel":"国籍","e2":"中国"},{"_id":"5ae70919b5db3b313047abde","e1":"奥迪A8L","rel":"品牌","e2":"奥迪"},{"_id":"5ae70919b5db3b313047abdf","e1":"欧洲","rel":"简称","e2":"欧洲"},{"_id":"5ae70919b5db3b313047abe0","e1":"克莱斯勒","rel":"公司名称","e2":"克莱斯勒"},{"_id":"5ae70919b5db3b313047abe1","e1":"Cullinan","rel":"外文名","e2":"Cullinan"},{"_id":"5ae70919b5db3b313047abe2","e1":"C-NCAP","rel":"简称","e2":"C-NCAP"},{"_id":"5ae70919b5db3b313047abe3","e1":"沃尔沃","rel":"主要农产品","e2":"XC60"},{"_id":"5ae70919b5db3b313047abe4","e1":"雪铁龙C4L","rel":"品牌","e2":"雪铁龙"},{"_id":"5ae70919b5db3b313047abe5","e1":"阿尔法·罗密欧","rel":"公司名称","e2":"阿尔法·罗密欧"},{"_id":"5ae70919b5db3b313047abe6","e1":"雷克萨斯","rel":"主要车型","e2":"RX"},{"_id":"5ae70919b5db3b313047abe7","e1":"马化腾","rel":"BaiduTAG","e2":"腾讯"},{"_id":"5ae70919b5db3b313047abe8","e1":"汉兰达","rel":"生产厂家","e2":"广汽丰田"},{"_id":"5ae70919b5db3b313047abe9","e1":"神龙汽车有限公司","rel":"公司名称","e2":"神龙汽车有限公司"},{"_id":"5ae70919b5db3b313047abea","e1":"比亚迪股份有限公司","rel":"创始人","e2":"王传福"},{"_id":"5ae70919b5db3b313047abeb","e1":"宾利","rel":"主要农产品","e2":"欧陆"},{"_id":"5ae70919b5db3b313047abec","e1":"鲁冠球","rel":"毕业院校","e2":"万向集团"},{"_id":"5ae70919b5db3b313047abed","e1":"捷克","rel":"最大城市","e2":"布拉格"}]